tropea_clustering/__init__.py
tropea_clustering/helpers.py
tropea_clustering/plot.py
tropea_clustering/plot_smooth.py
tropea_clustering/_internal/utilities.py
tropea_clustering/_internal/onion_old/classes.py
tropea_clustering/_internal/onion_old/first_classes.py
tropea_clustering/_internal/onion_old/functions.py
tropea_clustering/_internal/onion_old/main.py
tropea_clustering/_internal/onion_old/main_2d.py
tropea_clustering/_internal/onion_old/onion_multi.py
tropea_clustering/_internal/onion_old/onion_uni.py
tropea_clustering/_internal/onion_old/plot.py
tropea_clustering/_internal/onion_old/__pycache__/classes.cpython-313.pyc
tropea_clustering/_internal/onion_old/__pycache__/first_classes.cpython-313.pyc
tropea_clustering/_internal/onion_old/__pycache__/functions.cpython-313.pyc
tropea_clustering/_internal/onion_old/__pycache__/main.cpython-313.pyc
tropea_clustering/_internal/onion_old/__pycache__/main_2d.cpython-313.pyc
tropea_clustering/_internal/onion_old/__pycache__/onion_multi.cpython-313.pyc
tropea_clustering/_internal/onion_old/__pycache__/onion_uni.cpython-313.pyc
tropea_clustering/_internal/onion_old/__pycache__/plot.cpython-313.pyc
tropea_clustering/_internal/onion_smooth/first_classes.py
tropea_clustering/_internal/onion_smooth/functions.py
tropea_clustering/_internal/onion_smooth/main.py
tropea_clustering/_internal/onion_smooth/main_2d.py
tropea_clustering/_internal/onion_smooth/onion_multi.py
tropea_clustering/_internal/onion_smooth/onion_uni.py
tropea_clustering/_internal/onion_smooth/plot.py
tropea_clustering/_internal/onion_smooth/__pycache__/first_classes.cpython-313.pyc
tropea_clustering/_internal/onion_smooth/__pycache__/functions.cpython-313.pyc
tropea_clustering/_internal/onion_smooth/__pycache__/main.cpython-313.pyc
tropea_clustering/_internal/onion_smooth/__pycache__/main_2d.cpython-313.pyc
tropea_clustering/_internal/onion_smooth/__pycache__/onion_multi.cpython-313.pyc
tropea_clustering-2.1.1.dist-info/licenses/LICENSE
tropea_clustering-2.1.1.dist-info/METADATA
tropea_clustering-2.1.1.dist-info/WHEEL
tropea_clustering-2.1.1.dist-info/top_level.txt
tropea_clustering-2.1.1.dist-info/RECORD
