Metadata-Version: 2.4
Name: tropea-clustering
Version: 2.1.1
Summary: Code for unsupervised clustering of time-correlated data.
Maintainer-email: Matteo Becchi <bechmath@gmail.com>
Project-URL: github, https://github.com/matteobecchi/onion_clustering/
Project-URL: documentation, https://onion_clustering.readthedocs.io/en/latest/
Requires-Python: >=3.9
License-File: LICENSE
Requires-Dist: numpy
Requires-Dist: scipy
Requires-Dist: scikit-learn
Requires-Dist: matplotlib
Requires-Dist: plotly
Requires-Dist: kaleido
Provides-Extra: dev
Requires-Dist: mypy; extra == "dev"
Requires-Dist: pytest; extra == "dev"
Requires-Dist: pytest-cov; extra == "dev"
Requires-Dist: sphinx; extra == "dev"
Requires-Dist: sphinx-copybutton; extra == "dev"
Requires-Dist: build; extra == "dev"
Requires-Dist: twine; extra == "dev"
Requires-Dist: furo; extra == "dev"
Requires-Dist: numba; extra == "dev"
Requires-Dist: ruff; extra == "dev"
Dynamic: license-file
